mastermind/__init__.py
mastermind/mastermind_notebook.py
mastermind/img/game_capture.png
mastermind/notebooks/launch_game.ipynb
mastermind-0.7.dist-info/LICENSE
mastermind-0.7.dist-info/METADATA
mastermind-0.7.dist-info/WHEEL
mastermind-0.7.dist-info/top_level.txt
mastermind-0.7.dist-info/RECORD
