Metadata-Version: 2.1
Name: mastermind
Version: 0.7
Summary: Play mastermind with python !
Home-page: https://github.com/nicohlr/mastermind.git
Author: Nicolas Houlier
Author-email: nicolas.houlier@gmail.com
License: MIT
Keywords: mastermind notebook ipywidgets game
Platform: UNKNOWN
Classifier: License :: OSI Approved :: MIT License
Classifier: Programming Language :: Python :: 3.7
Requires-Dist: ipywidgets (>=7.4)
Requires-Dist: notebook-toggle-code
